Metadata-Version: 1.0
Name: jawad-distributions
Version: 0.1
Summary: Gaussian distributions
Home-page: UNKNOWN
Author: Jawad Rashid
Author-email: jawad@ndataconsulting.com
License: UNKNOWN
Platform: UNKNOWN
